{
  "db_name": "PostgreSQL",
  "query": "\n            SELECT\n                id AS \"id!: Uuid\",\n                team_id AS \"team_id!: Uuid\",\n                parent_id AS \"parent_id: Uuid\",\n                name,\n                local_path,\n                created_at AS \"created_at!: DateTime<Utc>\",\n                updated_at AS \"updated_at!: DateTime<Utc>\"\n            FROM document_folders\n            WHERE team_id = $1\n            ORDER BY position ASC, name ASC\n            ",
  "describe": {
    "columns": [
      {
        "ordinal": 0,
        "name": "id!: Uuid",
        "type_info": "Uuid"
      },
      {
        "ordinal": 1,
        "name": "team_id!: Uuid",
        "type_info": "Uuid"
      },
      {
        "ordinal": 2,
        "name": "parent_id: Uuid",
        "type_info": "Uuid"
      },
      {
        "ordinal": 3,
        "name": "name",
        "type_info": "Text"
      },
      {
        "ordinal": 4,
        "name": "local_path",
        "type_info": "Text"
      },
      {
        "ordinal": 5,
        "name": "created_at!: DateTime<Utc>",
        "type_info": "Timestamptz"
      },
      {
        "ordinal": 6,
        "name": "updated_at!: DateTime<Utc>",
        "type_info": "Timestamptz"
      }
    ],
    "parameters": {
      "Left": [
        "Uuid"
      ]
    },
    "nullable": [
      false,
      false,
      true,
      false,
      true,
      false,
      false
    ]
  },
  "hash": "edfdf7ae07903001f7e1eddf9196d14b453634201e4cba341fbf43508d5cd504"
}
