{
  "db_name": "PostgreSQL",
  "query": "SELECT c.id as \"id!: Uuid\",\n                      c.team_id as \"team_id!: Uuid\",\n                      c.tenant_workspace_id as \"tenant_workspace_id!: Uuid\",\n                      c.name,\n                      c.conversation_type,\n                      c.created_by,\n                      c.created_at as \"created_at!: DateTime<Utc>\",\n                      c.updated_at as \"updated_at!: DateTime<Utc>\"\n               FROM conversations c\n               INNER JOIN conversation_participants cp ON c.id = cp.conversation_id\n               WHERE cp.user_id = $1 AND c.team_id = $2\n               ORDER BY c.updated_at DESC",
  "describe": {
    "columns": [
      {
        "ordinal": 0,
        "name": "id!: Uuid",
        "type_info": "Uuid"
      },
      {
        "ordinal": 1,
        "name": "team_id!: Uuid",
        "type_info": "Uuid"
      },
      {
        "ordinal": 2,
        "name": "tenant_workspace_id!: Uuid",
        "type_info": "Uuid"
      },
      {
        "ordinal": 3,
        "name": "name",
        "type_info": "Text"
      },
      {
        "ordinal": 4,
        "name": "conversation_type",
        "type_info": "Text"
      },
      {
        "ordinal": 5,
        "name": "created_by",
        "type_info": "Text"
      },
      {
        "ordinal": 6,
        "name": "created_at!: DateTime<Utc>",
        "type_info": "Timestamptz"
      },
      {
        "ordinal": 7,
        "name": "updated_at!: DateTime<Utc>",
        "type_info": "Timestamptz"
      }
    ],
    "parameters": {
      "Left": [
        "Text",
        "Uuid"
      ]
    },
    "nullable": [
      false,
      false,
      false,
      true,
      false,
      false,
      false,
      false
    ]
  },
  "hash": "9e62cf51f9c8aafd9cfea94b1b7a64216f8928ff2877b4ac04ce54e3710fd869"
}
